{"version":1,"resource":"file:///home/morishita/Dev/LightStand/Backend/smart-pass-backend/src/card/card.service.ts","entries":[{"id":"45Zq.ts","timestamp":1689272615020},{"id":"jjli.ts","timestamp":1689272648557},{"id":"ri5E.ts","timestamp":1689272680467},{"id":"6qah.ts","timestamp":1689272721354},{"id":"5kq8.ts","timestamp":1689272734941},{"id":"RsMg.ts","timestamp":1689272789945},{"id":"asFK.ts","timestamp":1689272810225},{"id":"WSKY.ts","timestamp":1689273065449},{"id":"tKZ9.ts","timestamp":1689273226669},{"id":"ai8s.ts","timestamp":1689273247196},{"id":"lS7A.ts","source":"Add async modifier to containing function","timestamp":1689273255813},{"id":"KA5N.ts","timestamp":1689273363933},{"id":"QeXC.ts","timestamp":1689273384020},{"id":"dJyk.ts","timestamp":1689275061917},{"id":"Uamt.ts","timestamp":1689275175052},{"id":"xLnm.ts","timestamp":1689275451467},{"id":"rbkg.ts","timestamp":1689275731376},{"id":"hAMb.ts","timestamp":1689276007741},{"id":"ulbU.ts","timestamp":1689276035668},{"id":"7Pyw.ts","timestamp":1689276126465},{"id":"5tR3.ts","timestamp":1689276236432},{"id":"HsQ2.ts","timestamp":1689276263136},{"id":"XP5D.ts","timestamp":1689276291933},{"id":"UQDR.ts","timestamp":1689276343576},{"id":"zKjH.ts","timestamp":1689276399707},{"id":"wcpG.ts","timestamp":1689276413190},{"id":"KjD4.ts","timestamp":1689276442863},{"id":"SnBZ.ts","timestamp":1689276506324},{"id":"8bu4.ts","timestamp":1689276578051},{"id":"kugo.ts","timestamp":1689276665891},{"id":"CfDF.ts","timestamp":1689276682911},{"id":"Oqag.ts","timestamp":1689276715878},{"id":"FoHx.ts","timestamp":1689276740365},{"id":"PJ6O.ts","timestamp":1689276782275},{"id":"Co1V.ts","timestamp":1689276801625},{"id":"Zd8D.ts","timestamp":1689276899676},{"id":"79xn.ts","timestamp":1689276912869},{"id":"fSIL.ts","timestamp":1689276972760},{"id":"SnQc.ts","timestamp":1689277765895},{"id":"soZx.ts","timestamp":1689277790998},{"id":"tjXH.ts","timestamp":1689277837431},{"id":"MzrZ.ts","timestamp":1689278187582},{"id":"Vz8J.ts","timestamp":1689278511806},{"id":"uq0M.ts","source":"undoRedo.source","timestamp":1689278645353},{"id":"kETc.ts","timestamp":1689278760853},{"id":"Qwfy.ts","timestamp":1689278782963},{"id":"gmnC.ts","timestamp":1689278832947},{"id":"1H7r.ts","timestamp":1689278853003},{"id":"pOd4.ts","timestamp":1689278904730},{"id":"OgDQ.ts","timestamp":1689278943357}]}